{
  "rows_included_final": 1736,
  "anio_ing_act_fuente_distribution": {
    "DA_ANOINGRESO": 1736
  },
  "sem_ing_act_fuente_distribution": {
    "DA_PERIODOINGRESO": 1736
  },
  "anio_ing_ori_fuente_distribution": {
    "POLITICA_FOR_ING_ACT_FIJO_1": 1736
  },
  "sem_ing_ori_fuente_distribution": {
    "POLITICA_FOR_ING_ACT_FIJO_1": 1736
  },
  "niv_aca_fuente_distribution": {
    "INPUT_NIVEL": 1736
  },
  "fecha_matricula_fuente_distribution": {
    "POLITICA_COHORTE_ORIGEN_2026": 1724,
    "DA_FECHAMATRICULA": 12
  },
  "anio_ing_act_default_2026_rows": 0,
  "sem_ing_act_default_1_rows": 0,
  "anio_ing_ori_policy_rows": 1736,
  "sem_ing_ori_policy_rows": 1736,
  "niv_aca_default_1_rows": 0,
  "niv_aca_acotado_duracion_rows": 263,
  "niv_aca_acotado_cohorte_2026_rows": 8,
  "fecha_matricula_1900_rows": 1724,
  "fecha_matricula_1900_fuera_2026_rows": 1724,
  "fecha_matricula_1900_en_2026_rows": 0,
  "fecha_matricula_non1900_fuera_2026_rows": 0,
  "anio_ing_ori_diff_rows": 0,
  "sem_ing_ori_diff_rows": 0,
  "columnas_fase_3": {
    "Q_ANIO_ING_ACT": {
      "fuente_regla_definida": true,
      "transformacion_implementada": true,
      "validacion_qa_existe": true,
      "sin_default_silencioso": true,
      "auditable_en_filas_incluidas": true,
      "estado_final": "OK"
    },
    "R_SEM_ING_ACT": {
      "fuente_regla_definida": true,
      "transformacion_implementada": true,
      "validacion_qa_existe": true,
      "sin_default_silencioso": true,
      "auditable_en_filas_incluidas": true,
      "estado_final": "OK"
    },
    "S_ANIO_ING_ORI": {
      "fuente_regla_definida": true,
      "transformacion_implementada": true,
      "validacion_qa_existe": true,
      "sin_default_silencioso": true,
      "auditable_en_filas_incluidas": true,
      "estado_final": "OK"
    },
    "T_SEM_ING_ORI": {
      "fuente_regla_definida": true,
      "transformacion_implementada": true,
      "validacion_qa_existe": true,
      "sin_default_silencioso": true,
      "auditable_en_filas_incluidas": true,
      "estado_final": "OK"
    },
    "AA_NIV_ACA": {
      "fuente_regla_definida": true,
      "transformacion_implementada": true,
      "validacion_qa_existe": true,
      "sin_default_silencioso": true,
      "auditable_en_filas_incluidas": true,
      "estado_final": "OK"
    },
    "AD_FECHA_MATRICULA": {
      "fuente_regla_definida": true,
      "transformacion_implementada": true,
      "validacion_qa_existe": true,
      "sin_default_silencioso": true,
      "auditable_en_filas_incluidas": true,
      "estado_final": "OK"
    }
  }
}